eventique/EventsHandler.py
eventique/Listener.py
eventique/ThreadSharedSingleton.py
eventique/__init__.py
eventique-1.0.1.dist-info/METADATA
eventique-1.0.1.dist-info/WHEEL
eventique-1.0.1.dist-info/top_level.txt
eventique-1.0.1.dist-info/RECORD
