Metadata-Version: 2.1
Name: eventique
Version: 1.0.1
Summary: Light and standalone python events manager.
Home-page: https://github.com/hadamrd/eventique
Author: MAJDOUB Khalid
Author-email: majdoub.khalid@gmail.com
Classifier: Programming Language :: Python :: 3
Classifier: License :: OSI Approved :: MIT License
Classifier: Intended Audience :: Developers
